{
  "entities": {
    "AllocationRecord": {
      "title": "Allocation Record",
      "description": "A record of a single machine allocation session.",
      "type": "object",
      "properties": {
        "id": {
          "type": "string",
          "description": "Unique identifier for the record."
        },
        "date": {
          "type": "string",
          "format": "date-time",
          "description": "The timestamp when the allocation was saved."
        },
        "totalUnits": {
          "type": "integer",
          "description": "Total number of machines allocated."
        },
        "allocations": {
          "type": "object",
          "description": "A map of staff names to the number of machines they were assigned."
        }
      },
      "required": ["id", "date", "totalUnits", "allocations"]
    },
    "Staff": {
      "title": "Staff",
      "description": "A staff member who can be allocated machines.",
      "type": "object",
      "properties": {
        "id": {
          "type": "string",
          "description": "Unique identifier for the staff member."
        },
        "name": {
          "type": "string",
          "description": "Name of the staff member."
        },
        "region": {
          "type": "string",
          "enum": ["TW", "CN"],
          "description": "The region the staff member belongs to."
        },
        "active": {
          "type": "boolean",
          "description": "Whether the staff member is currently part of the rotation."
        }
      },
      "required": ["id", "name", "region", "active"]
    }
  },
  "firestore": {
    "/allocations/{recordId}": {
      "schema": "AllocationRecord",
      "description": "Collection of all machine allocation history."
    },
    "/staff/{staffId}": {
      "schema": "Staff",
      "description": "Collection of staff members."
    }
  }
}
